Metadata-Version: 2.1
Name: websocket-bridge-python
Version: 0.0.2
Summary: websocket-bridge Used for communication between Emacs and python
Home-page: https://github.com/ginqi7/websocket-bridge-python
Author: qiqi jin
Author-email: ginqi7@gmail.com
